odoo/addons/l10n_es_aeat_mod123/README.rst
odoo/addons/l10n_es_aeat_mod123/__init__.py
odoo/addons/l10n_es_aeat_mod123/__manifest__.py
odoo/addons/l10n_es_aeat_mod123/data/aeat_export_mod123_data.xml
odoo/addons/l10n_es_aeat_mod123/data/tax_code_map_mod123.xml
odoo/addons/l10n_es_aeat_mod123/i18n/bg.po
odoo/addons/l10n_es_aeat_mod123/i18n/ca.po
odoo/addons/l10n_es_aeat_mod123/i18n/cs.po
odoo/addons/l10n_es_aeat_mod123/i18n/de.po
odoo/addons/l10n_es_aeat_mod123/i18n/es.po
odoo/addons/l10n_es_aeat_mod123/i18n/es_CO.po
odoo/addons/l10n_es_aeat_mod123/i18n/es_CR.po
odoo/addons/l10n_es_aeat_mod123/i18n/es_ES.po
odoo/addons/l10n_es_aeat_mod123/i18n/eu.po
odoo/addons/l10n_es_aeat_mod123/i18n/fr.po
odoo/addons/l10n_es_aeat_mod123/i18n/gl.po
odoo/addons/l10n_es_aeat_mod123/i18n/hr.po
odoo/addons/l10n_es_aeat_mod123/i18n/l10n_es_aeat_mod123.pot
odoo/addons/l10n_es_aeat_mod123/i18n/nl.po
odoo/addons/l10n_es_aeat_mod123/i18n/pl.po
odoo/addons/l10n_es_aeat_mod123/i18n/pt.po
odoo/addons/l10n_es_aeat_mod123/i18n/pt_BR.po
odoo/addons/l10n_es_aeat_mod123/i18n/sl.po
odoo/addons/l10n_es_aeat_mod123/i18n/sv.po
odoo/addons/l10n_es_aeat_mod123/i18n/tr.po
odoo/addons/l10n_es_aeat_mod123/i18n/vi.po
odoo/addons/l10n_es_aeat_mod123/migrations/13.0.1.0.0/pre-migration.py
odoo/addons/l10n_es_aeat_mod123/models/__init__.py
odoo/addons/l10n_es_aeat_mod123/models/mod123.py
odoo/addons/l10n_es_aeat_mod123/readme/CONTRIBUTORS.rst
odoo/addons/l10n_es_aeat_mod123/readme/DESCRIPTION.rst
odoo/addons/l10n_es_aeat_mod123/readme/USAGE.rst
odoo/addons/l10n_es_aeat_mod123/security/ir.model.access.csv
odoo/addons/l10n_es_aeat_mod123/security/mod_123_security.xml
odoo/addons/l10n_es_aeat_mod123/static/description/icon.png
odoo/addons/l10n_es_aeat_mod123/static/description/icon_source.svg
odoo/addons/l10n_es_aeat_mod123/static/description/index.html
odoo/addons/l10n_es_aeat_mod123/tests/__init__.py
odoo/addons/l10n_es_aeat_mod123/tests/test_l10n_es_aeat_mod123.py
odoo13_addon_l10n_es_aeat_mod123-13.0.1.1.0.dist-info/METADATA
odoo13_addon_l10n_es_aeat_mod123-13.0.1.1.0.dist-info/WHEEL
odoo13_addon_l10n_es_aeat_mod123-13.0.1.1.0.dist-info/top_level.txt
odoo13_addon_l10n_es_aeat_mod123-13.0.1.1.0.dist-info/RECORD
