Metadata-Version: 2.1
Name: odoo13-addon-l10n-es-aeat-mod123
Version: 13.0.1.1.0
Summary: AEAT modelo 123
Home-page: https://github.com/OCA/l10n-spain
Author: Tecnativa, Spanish Localization Team, Odoo Community Association (OCA)
Author-email: support@odoo-community.org
License: AGPL-3
Platform: UNKNOWN
Classifier: Programming Language :: Python
Classifier: Framework :: Odoo
Classifier: License :: OSI Approved :: GNU Affero General Public License v3
Requires-Python: >=3.5
Requires-Dist: odoo13-addon-l10n-es-aeat
Requires-Dist: odoo (<13.1dev,>=13.0a)
